README.md
setup.py
displaylib/__init__.py
displaylib/math.py
displaylib.egg-info/PKG-INFO
displaylib.egg-info/SOURCES.txt
displaylib.egg-info/dependency_links.txt
displaylib.egg-info/top_level.txt
displaylib/ascii/__init__.py
displaylib/ascii/animation.py
displaylib/ascii/camera.py
displaylib/ascii/clock.py
displaylib/ascii/engine.py
displaylib/ascii/grapheme.py
displaylib/ascii/node.py
displaylib/ascii/screen.py
displaylib/ascii/surface.py
displaylib/ascii/texture.py
displaylib/ascii/networking/__init__.py
displaylib/ascii/networking/broadcast_server.py
displaylib/ascii/networking/client.py
displaylib/ascii/networking/server.py
displaylib/ascii/prefab/image.py
displaylib/ascii/prefab/label.py
displaylib/ascii/prefab/line.py
displaylib/ascii/prefab/sprite.py
displaylib/pygame/__init__.py
displaylib/pygame/constants.py
displaylib/pygame/engine.py
displaylib/pygame/node.py
displaylib/pygame/networking/__init__.py
displaylib/template/__init__.py
displaylib/template/engine.py
displaylib/template/node.py
displaylib/template/networking/__init__.py
displaylib/template/networking/broadcast_server.py
displaylib/template/networking/class_register.py
displaylib/template/networking/client.py
displaylib/template/networking/deserialize.py
displaylib/template/networking/serialize.py
displaylib/template/networking/server.py