Metadata-Version: 2.1
Name: displaylib
Version: 0.0.7
Summary: A collection of frameworks used to display ASCII or Pygame graphics
Home-page: https://github.com/Floating-Int/displaylib
Download-URL: https://pypi.org/project/displaylib/
Author: Floating-Int
Requires-Python: >=3.10
